setup.py
sentrycli/__init__.py
sentrycli/breadcrumbs.py
sentrycli/constants.py
sentrycli/event.py
sentrycli/group.py
sentrycli/main.py
sentrycli/preferences.py
sentrycli/query.py
sentrycli/table.py
sentrycli/utils.py
sentrycli.egg-info/PKG-INFO
sentrycli.egg-info/SOURCES.txt
sentrycli.egg-info/dependency_links.txt
sentrycli.egg-info/entry_points.txt
sentrycli.egg-info/not-zip-safe
sentrycli.egg-info/requires.txt
sentrycli.egg-info/top_level.txt