Metadata-Version: 1.1
Name: sentrycli
Version: 1.5.0
Summary: CLI scripts to query and analyze data gathered by Sentry
Home-page: https://github.com/operasoftware/sentrycli/
Author: Opera Wrocław Services
Author-email: svc-code@opera.com
License: MIT
Download-URL: https://github.com/operasoftware/sentrycli/tarball/1.5.0
Keywords: sentry cli aggregation analysis events errors logging
Platform: UNKNOWN
